{"scriptId":"3","url":"deno:core/core.js","functions":[{"functionName":"setPromise","ranges":[{"startOffset":536,"endOffset":901,"count":287},{"startOffset":725,"endOffset":830,"count":0}],"isBlockCoverage":true},{"functionName":"getPromise","ranges":[{"startOffset":905,"endOffset":1356,"count":287},{"startOffset":1074,"endOffset":1188,"count":0}],"isBlockCoverage":true},{"functionName":"newPromise","ranges":[{"startOffset":1360,"endOffset":1607,"count":287}],"isBlockCoverage":true},{"functionName":"","ranges":[{"startOffset":1441,"endOffset":1521,"count":287}],"isBlockCoverage":true},{"functionName":"handleAsyncMsgFromRust","ranges":[{"startOffset":1825,"endOffset":2069,"count":287}],"isBlockCoverage":true},{"functionName":"dispatch","ranges":[{"startOffset":2073,"endOffset":2199,"count":1367}],"isBlockCoverage":true},{"functionName":"unwrapOpResult","ranges":[{"startOffset":2560,"endOffset":3120,"count":1367},{"startOffset":2676,"endOffset":2693,"count":512},{"startOffset":2695,"endOffset":3100,"count":0}],"isBlockCoverage":true},{"functionName":"opAsync","ranges":[{"startOffset":3124,"endOffset":3452,"count":287},{"startOffset":3359,"endOffset":3393,"count":0}],"isBlockCoverage":true},{"functionName":"opSync","ranges":[{"startOffset":3456,"endOffset":3582,"count":1080}],"isBlockCoverage":true},{"functionName":"resources","ranges":[{"startOffset":3586,"endOffset":3667,"count":170}],"isBlockCoverage":true}]}